LICENSE
MANIFEST.in
README.rst
requirements-test-py32.txt
requirements-test.txt
setup.cfg
setup.py
calleee/__init__.py
calleee/_compat.py
calleee/attributes.py
calleee/base.py
calleee/collections.py
calleee/functions.py
calleee/general.py
calleee/numbers.py
calleee/objects.py
calleee/operators.py
calleee/strings.py
calleee/types.py
calleee.egg-info/PKG-INFO
calleee.egg-info/SOURCES.txt
calleee.egg-info/dependency_links.txt
calleee.egg-info/top_level.txt